{
  "metadata": {
    "schema_version": "1.0.0",
    "resource_group": "shared",
    "language": "es-CO",
    "domain": "restaurante_colombiano_de_comida_de_mar",
    "purpose": "Contrato canónico compartido por Matcher, Lemmas, Resolver y datasets",
    "naming_policy": "snake_case; una acción comunicativa por subintención"
  },
  "intents": {
    "catalogo": {
      "description": "Consultas sobre la oferta gastronómica y las propiedades de los platos.",
      "subintents": {
        "comparar_productos": "Compara dos o más productos por una cualidad explícita.",
        "consultar_categoria": "Consulta qué productos pertenecen a una categoría de la carta.",
        "consultar_categoria_por_restriccion": "Busca una categoría u opción compatible con una restricción alimentaria.",
        "consultar_definicion_preparacion": "Pregunta qué significa una técnica o preparación culinaria.",
        "consultar_detalle_producto": "Pregunta por ingredientes, acompañamientos o características de un producto identificado.",
        "consultar_disponibilidad_producto": "Pregunta si un producto se encuentra disponible.",
        "consultar_preparacion": "Busca productos elaborados con una preparación determinada.",
        "consultar_preparacion_producto": "Pregunta si un producto admite una preparación determinada.",
        "consultar_producto": "Pregunta de manera general si el restaurante ofrece un producto."
      }
    },
    "domicilio": {
      "description": "Consultas sobre cobertura, costo, tiempo y referencias de entrega a domicilio.",
      "subintents": {
        "consultar_domicilio": "Consulta condiciones generales, cobertura, costo o tiempo del domicilio.",
        "consultar_domicilio_grupal": "Consulta logística de entrega para un pedido grupal.",
        "usar_direccion_previa": "Solicita usar una dirección registrada en el contexto conversacional."
      }
    },
    "horario_ubicacion": {
      "description": "Información física y temporal del establecimiento.",
      "subintents": {
        "consultar_horario": "Consulta días u horas de atención.",
        "consultar_instalacion": "Consulta instalaciones o facilidades disponibles para clientes.",
        "consultar_parqueadero": "Consulta disponibilidad o condiciones del parqueadero.",
        "consultar_ubicacion": "Consulta dirección o ubicación del restaurante."
      }
    },
    "menu": {
      "description": "Solicitudes relacionadas con la carta como documento o vista general.",
      "subintents": {
        "consultar_cambios_menu": "Pregunta qué cambió en la carta.",
        "consultar_menu_general": "Pregunta de forma abierta qué ofrece el restaurante.",
        "reenviar_menu": "Solicita volver a enviar una carta previamente compartida.",
        "solicitar_menu": "Solicita recibir o visualizar la carta."
      }
    },
    "operacion": {
      "description": "Servicios operativos complementarios al consumo y al pedido.",
      "subintents": {
        "consultar_empaque": "Consulta separación, marcado o presentación de pedidos.",
        "consultar_facturacion": "Consulta factura, factura electrónica o requisitos tributarios.",
        "consultar_pedido_programado": "Consulta o solicita programar una entrega para una hora posterior.",
        "consultar_servicio": "Consulta un servicio complementario no cubierto por otra intención."
      }
    },
    "pago": {
      "description": "Consultas sobre instrumentos y combinación de pagos.",
      "subintents": {
        "consultar_medio_pago": "Pregunta si se acepta un medio de pago.",
        "consultar_pago_mixto": "Pregunta si puede dividir el pago entre dos o más medios."
      }
    },
    "pedido": {
      "description": "Creación y modificación transaccional de un pedido.",
      "subintents": {
        "agregar_producto_pedido": "Añade una referencia de producto a un pedido en curso.",
        "agregar_productos_pedido": "Añade explícitamente varias referencias o unidades a un pedido.",
        "indicar_cantidad": "Indica una cantidad apoyándose en el producto activo del contexto.",
        "iniciar_pedido": "Expresa la voluntad de pedir un producto.",
        "iniciar_pedido_grupal": "Inicia un pedido para varias personas sin detallar todavía los productos.",
        "repetir_pedido": "Solicita repetir un pedido conocido por el contexto.",
        "seleccionar_preparacion": "Selecciona una preparación para el producto activo.",
        "solicitar_modificacion": "Añade, retira o sustituye ingredientes o preparaciones."
      }
    },
    "precio": {
      "description": "Consultas de precios y presupuesto.",
      "subintents": {
        "consultar_precio_producto": "Pregunta el precio de un producto identificado.",
        "consultar_precios_generales": "Solicita precios sin identificar un producto.",
        "solicitar_recomendacion_por_presupuesto": "Busca opciones compatibles con un presupuesto o criterio de economía."
      }
    },
    "recomendacion": {
      "description": "Solicitudes de orientación para elegir un plato.",
      "subintents": {
        "solicitar_recomendacion": "Solicita una recomendación general o por preferencia culinaria.",
        "solicitar_recomendacion_por_alergia": "Solicita una recomendación compatible con una alergia.",
        "solicitar_recomendacion_por_restriccion": "Solicita una recomendación compatible con una restricción no necesariamente alérgica."
      }
    },
    "reserva_evento": {
      "description": "Reservas de mesa y servicios para grupos o eventos.",
      "subintents": {
        "consultar_eventos": "Consulta capacidad o condiciones para realizar eventos.",
        "consultar_reserva": "Consulta condiciones, costo o disponibilidad de una reserva.",
        "solicitar_evento": "Solicita una propuesta o gestión para un evento.",
        "solicitar_reserva": "Solicita reservar una mesa o espacio."
      }
    },
    "seguridad_alimentaria": {
      "description": "Consultas que requieren tratamiento conservador por riesgo alimentario.",
      "subintents": {
        "consultar_alergenos": "Consulta presencia de alérgenos o ingredientes sensibles.",
        "consultar_contaminacion_cruzada": "Consulta separación de aceite, utensilios o superficies."
      }
    },
    "social": {
      "description": "Actos sociales que no requieren una operación comercial.",
      "subintents": {
        "agradecer": "Expresa agradecimiento o cierre cortés."
      }
    }
  },
  "context_dependent_subintents": [
    "domicilio.usar_direccion_previa",
    "menu.reenviar_menu",
    "pedido.agregar_producto_pedido",
    "pedido.indicar_cantidad",
    "pedido.repetir_pedido",
    "pedido.seleccionar_preparacion"
  ]
}
